Authors
ChangeLog
License
MANIFEST
setup.py
RosterConfigManager.egg-info/PKG-INFO
RosterConfigManager.egg-info/SOURCES.txt
RosterConfigManager.egg-info/dependency_links.txt
RosterConfigManager.egg-info/requires.txt
RosterConfigManager.egg-info/top_level.txt
docs/html/.buildinfo
docs/html/genindex.html
docs/html/index.html
docs/html/objects.inv
docs/html/py-modindex.html
docs/html/roster_config_manager.html
docs/html/search.html
docs/html/searchindex.js
docs/html/_modules/index.html
docs/html/_modules/roster_config_manager/db_recovery.html
docs/html/_modules/roster_config_manager/tree_exporter.html
docs/html/_modules/roster_config_manager/zone_exporter_lib.html
docs/html/_modules/roster_config_manager/zone_importer_lib.html
docs/html/_sources/index.txt
docs/html/_sources/roster_config_manager.txt
docs/html/_static/ajax-loader.gif
docs/html/_static/basic.css
docs/html/_static/comment-bright.png
docs/html/_static/comment-close.png
docs/html/_static/comment.png
docs/html/_static/default.css
docs/html/_static/doctools.js
docs/html/_static/down-pressed.png
docs/html/_static/down.png
docs/html/_static/file.png
docs/html/_static/jquery.js
docs/html/_static/minus.png
docs/html/_static/plus.png
docs/html/_static/pygments.css
docs/html/_static/searchtools.js
docs/html/_static/sidebar.js
docs/html/_static/underscore.js
docs/html/_static/up-pressed.png
docs/html/_static/up.png
docs/html/_static/websupport.js
roster_config_manager/__init__.py
roster_config_manager/db_recovery.py
roster_config_manager/tree_exporter.py
roster_config_manager/zone_exporter_lib.py
roster_config_manager/zone_importer_lib.py
scripts/dnscheckconfig
scripts/dnsconfigsync
scripts/dnsexportconfig
scripts/dnsrecover
scripts/dnstreeexport
scripts/dnsversioncheck
scripts/dnszonecompare
scripts/dnszoneimporter